opnsense_api/__init__.py
opnsense_api/firewall/__init__.py
opnsense_api/firewall/alias_controller.py
opnsense_api/firewall/filter_controller.py
opnsense_api/unbound/__init__.py
opnsense_api/unbound/alias_controller.py
opnsense_api/unbound/domain_controller.py
opnsense_api/unbound/host_controller.py
opnsense_api/unbound/util.py
opnsense_api/util/__init__.py
opnsense_api/util/parse.py
opnsense_api/util/validate.py
python_opnsense-1.0.4.dist-info/LICENSE
python_opnsense-1.0.4.dist-info/METADATA
python_opnsense-1.0.4.dist-info/WHEEL
python_opnsense-1.0.4.dist-info/top_level.txt
python_opnsense-1.0.4.dist-info/RECORD
