Metadata-Version: 2.1
Name: python-opnsense
Version: 1.0.4
Summary: A python library that interacts with an Opnsense API
Home-page: https://github.com/turnbros/python-opnsense
Download-URL: https://github.com/turnbros/python-opnsense/releases/tag/1.0.4
Author: Dylan Turnbull
Author-email: dylanturn@gmail.com
License: apache-2.0
Keywords: turnbros,opnsense
Classifier: Programming Language :: Python :: 3
Classifier: License :: OSI Approved :: Apache Software License
Classifier: Operating System :: OS Independent
Requires-Python: >=3.8
License-File: LICENSE
